LLMlight/LLMlight.py
LLMlight/RAG.py
LLMlight/__init__.py
LLMlight/examples.py
LLMlight/memory.py
LLMlight/read_outlook.py
LLMlight/utils.py
llmlight-0.5.1.dist-info/licenses/LICENSE
llmlight-0.5.1.dist-info/METADATA
llmlight-0.5.1.dist-info/WHEEL
llmlight-0.5.1.dist-info/top_level.txt
llmlight-0.5.1.dist-info/RECORD
