Metadata-Version: 2.4
Name: LLMlight
Version: 0.5.1
Summary: LLMlight is a Python library for ...
Author-email: Erdogan Taskesen <erdogant@gmail.com>
License-Expression: MIT
Project-URL: Homepage, https://erdogant.github.io/LLMlight
Project-URL: Download, https://github.com/erdogant/LLMlight/archive/{version}.tar.gz
Keywords: Python,LLM,large language model,NLP,text generation,embedding,sentence transformer,document analysis,AI,machine learning
Classifier: Programming Language :: Python :: 3
Classifier: Operating System :: OS Independent
Classifier: Intended Audience :: Education
Classifier: Intended Audience :: Science/Research
Classifier: Operating System :: Unix
Classifier: Operating System :: Microsoft :: Windows
Classifier: Operating System :: MacOS
Classifier: Topic :: Scientific/Engineering :: Artificial Intelligence
Requires-Python: >=3
License-File: LICENSE
Requires-Dist: sentence_transformers
Requires-Dist: scikit-learn
Requires-Dist: llama-cpp-python
Requires-Dist: json-repair
Requires-Dist: pymupdf
Requires-Dist: torch
Requires-Dist: requests
Requires-Dist: memvid
Requires-Dist: ipywidgets
Requires-Dist: distfit
Dynamic: license-file
